LICENSE
MANIFEST.in
README.rst
requirements.txt
setup.cfg
setup.py
nordnm/__init__.py
nordnm/__main__.py
nordnm/benchmarking.py
nordnm/credentials.py
nordnm/networkmanager.py
nordnm/nordapi.py
nordnm/nordnm.py
nordnm/paths.py
nordnm/settings.py
nordnm/utils.py
nordnm.egg-info/PKG-INFO
nordnm.egg-info/SOURCES.txt
nordnm.egg-info/dependency_links.txt
nordnm.egg-info/entry_points.txt
nordnm.egg-info/not-zip-safe
nordnm.egg-info/requires.txt
nordnm.egg-info/top_level.txt