Metadata-Version: 1.1
Name: nordnm
Version: 0.6.1
Summary: A CLI tool for automating the importing, securing and usage of NordVPN OpenVPN servers through NetworkManager.
Home-page: https://github.com/Chadsr/NordVPN-NetworkManager
Author: Ross Chadwick
Author-email: ross@rchadwick.co.uk
License: GNU General Public License v3 or later (GPLv3+)
Keywords: openvpn,nordvpn,networkmanager,network-manager,vpn
Platform: GNU/Linux
Platform: Ubuntu
Platform: Debian
Platform: Kali
Platform: CentOS
Platform: Arch
Platform: Fedora
Classifier: Environment :: Console
Classifier: Intended Audience :: End Users/Desktop
Classifier: Intended Audience :: System Administrators
Classifier: Intended Audience :: Developers
Classifier: Topic :: Internet
Classifier: Topic :: Desktop Environment :: Gnome
Classifier: Topic :: Utilities
Classifier: Topic :: Security
Classifier: Topic :: System :: Networking
Classifier: License :: OSI Approved :: GNU General Public License v3 or later (GPLv3+)
Classifier: Natural Language :: English
Classifier: Operating System :: POSIX :: Linux
Classifier: Programming Language :: Python :: 3 :: Only
Classifier: Programming Language :: Python :: 3.5
Classifier: Programming Language :: Python :: 3.6
